{
    "sig": {
        "version": 2,
        "domain": {
            "name": "EAS Attestation",
            "version": "0.26",
            "chainId": "11155111",
            "verifyingContract": "0xC2679fBD37d54388Ce493F1DB75320D236e1815e"
        },
        "primaryType": "Attest",
        "types": {
            "Attest": [
                {
                    "name": "version",
                    "type": "uint16"
                },
                {
                    "name": "schema",
                    "type": "bytes32"
                },
                {
                    "name": "recipient",
                    "type": "address"
                },
                {
                    "name": "time",
                    "type": "uint64"
                },
                {
                    "name": "expirationTime",
                    "type": "uint64"
                },
                {
                    "name": "revocable",
                    "type": "bool"
                },
                {
                    "name": "refUID",
                    "type": "bytes32"
                },
                {
                    "name": "data",
                    "type": "bytes"
                },
                {
                    "name": "salt",
                    "type": "bytes32"
                }
            ]
        },
        "signature": {
            "r": "0x9079eddfd65f5c3ac938d1eac7c9f9c4fd8cf04d0c5ce6a303fa15bddcb24c86",
            "s": "0x097684fba28ad8cba8d92d3f20538b8e9a5cf1414266e5ecbf498eb36ce9f365",
            "v": 27
        },
        "uid": "0xa9e96b99272cdd97c8448f60fba7f35cca658c1360c2be2fbb4fc23abfbc9482",
        "message": {
            "version": 2,
            "schema": "0xe102b6f4e9491f87a8ca24a7bb9ccab0bdbc57cc2d58dacc38295c349f17542e",
            "recipient": "0x0000000000000000000000000000000000000000",
            "time": "1727107412",
            "expirationTime": "0",
            "refUID": "0x0000000000000000000000000000000000000000000000000000000000000000",
            "revocable": true,
            "data": "0x000000000000000000000000000000000000000000000000000000003e4c3180",
            "nonce": "0",
            "salt": "0xa654812efb967797e17698da4861fa9c3157d530af5a5196fa00833e52f69249"
        }
    },
    "signer": "0x7242Ccc30D68fca5cd8aEfc0ffbb545A1804439F"
}